{"products":[{"Deskripsi":"Daily Task, Broadcast, Spend Waveplate, Fantasies","Gambar":"assets/images/products/wuwa/a081915ab34aade7d149.webp","Gambar_Sumber":"https://cdn2.steamgriddb.com/icon_thumb/77875aea8d863f84d40b43f1d9b1e4f4.png","Game":"WUTHERING WAVES","Game_Key":"wuwa","Harga_Asli":70000,"Harga_Diskon":65000,"ID":"WUWA-P003","Kategori":"Daily","Nama_Paket":"Rawat Akun 1 Bulan (LITE)","Posisi_Gambar":"","Status":"Ready","Tampilan_Gambar":""},{"Deskripsi":"Spend Battery, Daily Errands, Eridu City Fund, Claim Weekly Stamp","Gambar":"assets/images/products/zzz/5a87b681e545943b3d9d.webp","Gambar_Sumber":"https://cdn2.steamgriddb.com/icon_thumb/64d79c921b451019fc7997d5d1ffd181.png","Game":"ZENLESS ZONE ZERO","Game_Key":"zzz","Harga_Asli":69000,"Harga_Diskon":65000,"ID":"ZZZ-P003","Kategori":"Daily","Nama_Paket":"Rawat Akun 1 Bulan (LITE)","Posisi_Gambar":"","Status":"Ready","Tampilan_Gambar":""},{"Deskripsi":"Daily Assignment, Nameless Honor, Spend Trailblazer","Gambar":"assets/images/products/hsr/c0d636dc65460a945799.webp","Gambar_Sumber":"https://cdn2.steamgriddb.com/icon_thumb/e52da5a31de788599378924f0e639557.png","Game":"HONKAI STAR RAIL","Game_Key":"hsr","Harga_Asli":70000,"Harga_Diskon":65000,"ID":"HSR-P003","Kategori":"Daily","Nama_Paket":"Rawat Akun 1 Bulan (LITE)","Posisi_Gambar":"","Status":"Ready","Tampilan_Gambar":""},{"Deskripsi":"Spend Resin, Daily Commision, Claim Battle Pass","Gambar":"assets/images/products/genshin/e1a300938e6ddfeae4fd.webp","Gambar_Sumber":"https://cdn2.steamgriddb.com/icon_thumb/54795ec619ebda94c86d00184861c96f.png","Game":"GENSHIN IMPACT","Game_Key":"genshin","Harga_Asli":80000,"Harga_Diskon":60000,"ID":"GI-P004","Kategori":"Rawat Akun","Nama_Paket":"Rawat Akun (LITE)","Posisi_Gambar":"","Status":"Ready","Tampilan_Gambar":""},{"Deskripsi":"Nodkrai 100% Exploration ","Gambar":"","Game":"GENSHIN IMPACT","Game_Key":"genshin","Harga_Asli":600000,"Harga_Diskon":560000,"ID":"GI-P026","Kategori":"Explore","Nama_Paket":"Explore Nodkrai","Posisi_Gambar":"","Status":"Ready","Tampilan_Gambar":""},{"Deskripsi":"Lahai Roi","Gambar":"","Game":"WUTHERING WAVES","Game_Key":"wuwa","Harga_Asli":25000,"Harga_Diskon":23000,"ID":"WUWA-P047","Kategori":"Explore","Nama_Paket":"Explore Giant's Gaze","Posisi_Gambar":"","Status":"Ready","Tampilan_Gambar":""}],"ratings":{"genshin":{"average":4.3,"total":3},"hsr":{"average":5.0,"total":1},"wuwa":{"average":5.0,"total":1},"zzz":{"average":5.0,"total":1}},"success":true}
